microblocks/__init__.py
microblocks-0.10.0.dist-info/AUTHORS.rst
microblocks-0.10.0.dist-info/LICENSE
microblocks-0.10.0.dist-info/METADATA
microblocks-0.10.0.dist-info/WHEEL
microblocks-0.10.0.dist-info/top_level.txt
microblocks-0.10.0.dist-info/RECORD
