Metadata-Version: 2.1
Name: microblocks
Version: 0.10.0
Summary: Python Boilerplate contains all the boilerplate you need to create a Python package.
Home-page: https://github.com/wwj718/microblocks_messaging_library
Author: Wenjie Wu
Author-email: wuwenjie718@gmail.com
License: GNU General Public License v3
Keywords: MicroBlocks
Classifier: Development Status :: 2 - Pre-Alpha
Classifier: Intended Audience :: Developers
Classifier: License :: OSI Approved :: GNU General Public License v3 (GPLv3)
Classifier: Natural Language :: English
Classifier: Programming Language :: Python :: 3.6
Classifier: Programming Language :: Python :: 3.7
Classifier: Programming Language :: Python :: 3.8
License-File: LICENSE
License-File: AUTHORS.rst
Requires-Dist: pyserial ==3.5
Requires-Dist: adafruit-circuitpython-ble ==10.0.7
Requires-Dist: dynatalk ==0.7.3
